<?xml version="1.0" encoding="UTF-8"?>
<analysisEngineDescription xmlns="http://uima.apache.org/resourceSpecifier">
    <frameworkImplementation>org.apache.uima.java</frameworkImplementation>
    <primitive>true</primitive>
    <annotatorImplementationName>de.tudarmstadt.ukp.dkpro.core.matetools.MateSemanticRoleLabeler</annotatorImplementationName>
    <analysisEngineMetaData>
        <name>de.tudarmstadt.ukp.dkpro.core.matetools.MateSemanticRoleLabeler</name>
        <description>DKPro Annotator for the MateTools Semantic Role Labeler.
&lt;p&gt;
Please cite the following paper, if you use the semantic role labeler
Anders Björkelund, Love Hafdell, and Pierre Nugues.  Multilingual semantic role labeling. 
In Proceedings of The Thirteenth Conference on Computational Natural Language Learning (CoNLL-2009),
pages 43--48, Boulder, June 4--5 2009. 
&lt;/p&gt;</description>
        <version>1.8.0-SNAPSHOT</version>
        <vendor>DKPro Core Project</vendor>
        <copyright>Copyright 2010-2015
                            Ubiquitous Knowledge Processing (UKP) Lab
                            Technische Universität Darmstadt</copyright>
        <configurationParameters>
            <configurationParameter>
                <name>language</name>
                <description>Use this language instead of the document language to resolve the model.</description>
                <type>String</type>
                <multiValued>false</multiValued>
                <mandatory>false</mandatory>
            </configurationParameter>
            <configurationParameter>
                <name>modelLocation</name>
                <description>Load the model from this location instead of locating the model automatically.</description>
                <type>String</type>
                <multiValued>false</multiValued>
                <mandatory>false</mandatory>
            </configurationParameter>
            <configurationParameter>
                <name>modelVariant</name>
                <description>Override the default variant used to locate the model.</description>
                <type>String</type>
                <multiValued>false</multiValued>
                <mandatory>false</mandatory>
            </configurationParameter>
        </configurationParameters>
        <configurationParameterSettings/>
        <typeSystemDescription/>
        <typePriorities/>
        <fsIndexCollection/>
        <capabilities>
            <capability>
                <inputs>
                    <type>de.tudarmstadt.ukp.dkpro.core.api.segmentation.type.Sentence</type>
                    <type>de.tudarmstadt.ukp.dkpro.core.api.segmentation.type.Token</type>
                    <type>de.tudarmstadt.ukp.dkpro.core.api.lexmorph.type.pos.POS</type>
                    <type>de.tudarmstadt.ukp.dkpro.core.api.segmentation.type.Lemma</type>
                    <type>de.tudarmstadt.ukp.dkpro.core.api.syntax.type.dependency.Dependency</type>
                </inputs>
                <outputs>
                    <type>de.tudarmstadt.ukp.dkpro.core.api.semantics.type.SemanticPredicate</type>
                    <type>de.tudarmstadt.ukp.dkpro.core.api.semantics.type.SemanticArgument</type>
                </outputs>
                <languagesSupported/>
            </capability>
        </capabilities>
        <operationalProperties>
            <modifiesCas>true</modifiesCas>
            <multipleDeploymentAllowed>false</multipleDeploymentAllowed>
            <outputsNewCASes>false</outputsNewCASes>
        </operationalProperties>
    </analysisEngineMetaData>
</analysisEngineDescription>
